pwm/__init__.py
pwm/__main__.py
pwm_lib-0.0.1.dev1.dist-info/DESCRIPTION.rst
pwm_lib-0.0.1.dev1.dist-info/METADATA
pwm_lib-0.0.1.dev1.dist-info/RECORD
pwm_lib-0.0.1.dev1.dist-info/WHEEL
pwm_lib-0.0.1.dev1.dist-info/metadata.json
pwm_lib-0.0.1.dev1.dist-info/top_level.txt
