Metadata-Version: 2.0
Name: pwm-lib
Version: 0.0.1.dev1
Summary: PWM is just a DRY library.
Home-page: https://gitlab.com/paip-web/pwm
Author: Patryk Adamczyk
Author-email: patrykadamczyk@paipweb.com
License: MIT
Keywords: development library
Platform: UNKNOWN
Classifier: Development Status :: 1 - Planning
Classifier: Intended Audience :: Developers
Classifier: Intended Audience :: Information Technology
Classifier: Intended Audience :: System Administrators
Classifier: Topic :: Software Development
Classifier: Topic :: Software Development :: Build Tools
Classifier: Topic :: Utilities
Classifier: License :: OSI Approved :: MIT License
Classifier: Programming Language :: Python :: 3
Classifier: Programming Language :: Python :: 3.6
Classifier: Programming Language :: Python :: 3.7
Classifier: Programming Language :: Python :: 3 :: Only
Classifier: Operating System :: OS Independent
Classifier: Operating System :: Microsoft :: Windows
Classifier: Operating System :: Microsoft :: Windows :: Windows 7
Classifier: Operating System :: Microsoft :: Windows :: Windows 10
Classifier: Operating System :: POSIX :: Linux
Classifier: Environment :: Console
Requires-Python: ~=3.5
Provides-Extra: setup
Requires-Dist: collective.checkdocs; extra == 'setup'
Requires-Dist: twine; extra == 'setup'
Requires-Dist: wheel; extra == 'setup'
Provides-Extra: test
Requires-Dist: coverage; extra == 'test'
Requires-Dist: green; extra == 'test'
Requires-Dist: pytest; extra == 'test'
